odoo/addons/stock_reserve_rule/README.rst
odoo/addons/stock_reserve_rule/__init__.py
odoo/addons/stock_reserve_rule/__manifest__.py
odoo/addons/stock_reserve_rule/demo/product_demo.xml
odoo/addons/stock_reserve_rule/demo/stock_inventory_demo.xml
odoo/addons/stock_reserve_rule/demo/stock_location_demo.xml
odoo/addons/stock_reserve_rule/demo/stock_picking_demo.xml
odoo/addons/stock_reserve_rule/demo/stock_reserve_rule_demo.xml
odoo/addons/stock_reserve_rule/i18n/stock_reserve_rule.pot
odoo/addons/stock_reserve_rule/models/__init__.py
odoo/addons/stock_reserve_rule/models/stock_location.py
odoo/addons/stock_reserve_rule/models/stock_move.py
odoo/addons/stock_reserve_rule/models/stock_quant.py
odoo/addons/stock_reserve_rule/models/stock_reserve_rule.py
odoo/addons/stock_reserve_rule/readme/CONFIGURE.rst
odoo/addons/stock_reserve_rule/readme/CONTRIBUTORS.rst
odoo/addons/stock_reserve_rule/readme/DESCRIPTION.rst
odoo/addons/stock_reserve_rule/readme/USAGE.rst
odoo/addons/stock_reserve_rule/security/ir.model.access.csv
odoo/addons/stock_reserve_rule/security/stock_reserve_rule_security.xml
odoo/addons/stock_reserve_rule/static/description/icon.png
odoo/addons/stock_reserve_rule/static/description/index.html
odoo/addons/stock_reserve_rule/tests/__init__.py
odoo/addons/stock_reserve_rule/tests/test_reserve_rule.py
odoo/addons/stock_reserve_rule/views/stock_reserve_rule_views.xml
odoo12_addon_stock_reserve_rule-12.0.1.0.0.99.dev4.dist-info/METADATA
odoo12_addon_stock_reserve_rule-12.0.1.0.0.99.dev4.dist-info/WHEEL
odoo12_addon_stock_reserve_rule-12.0.1.0.0.99.dev4.dist-info/top_level.txt
odoo12_addon_stock_reserve_rule-12.0.1.0.0.99.dev4.dist-info/RECORD
